indigenous_claims/__init__.py
indigenous_claims/indigenous_landclaims.py
indigenous_claims-0.1.dist-info/METADATA
indigenous_claims-0.1.dist-info/WHEEL
indigenous_claims-0.1.dist-info/entry_points.txt
indigenous_claims-0.1.dist-info/top_level.txt
indigenous_claims-0.1.dist-info/RECORD
