Metadata-Version: 2.1
Name: indigenous_claims
Version: 0.1
Requires-Dist: pandas
